{
  "noiseKey": {
    "private": {
      "type": "Buffer",
      "data": "IFZ9Si9sJXCiS3aUxbQeyN1BlNQaJuUlhqiWwHNh5lQ="
    },
    "public": {
      "type": "Buffer",
      "data": "JDoaVrA6mAO8cYI5PGexMN2LscxI4eP42QCVCp2iWXM="
    }
  },
  "pairingEphemeralKeyPair": {
    "private": {
      "type": "Buffer",
      "data": "sCqxK5Id0V+N1BN0egu0zPiiH9Fu/CA+0xMoyJ7Z5Xo="
    },
    "public": {
      "type": "Buffer",
      "data": "XxjNkA1OaC+g3bdtLjfLDZN1BnsE52w6vzZ3IxHYyUM="
    }
  },
  "signedIdentityKey": {
    "private": {
      "type": "Buffer",
      "data": "QNZ3OaaOGiWBefMAU0N2HQ0hACnPqPncQdsdEHJuvVQ="
    },
    "public": {
      "type": "Buffer",
      "data": "pSY9vBoz+wWrN0jeciRx/fPP4GYl1NTed2Jf9yRgvwg="
    }
  },
  "signedPreKey": {
    "keyPair": {
      "private": {
        "type": "Buffer",
        "data": "AIU9y/AB1Cmh5THOmKuh+nV4ynkylMmIJC55Dy/owWU="
      },
      "public": {
        "type": "Buffer",
        "data": "NMcpFt6QqKprJSzQimMAy45oPOi6Fy0qYDTx4udD+EM="
      }
    },
    "signature": {
      "type": "Buffer",
      "data": "dk1RWKe/Fo4QD67JDZFvpnsqdXj3u4ANoVPiZeEk6SytCCZw61nSn9TXRZIN03cc1r3coKnIf2dQIhnTbgUeig=="
    },
    "keyId": 1
  },
  "registrationId": 139,
  "advSecretKey": "KEQuiog9HveMsbC3zdDbClKEa/MzmnmyrYPCjcdZiDM=",
  "processedHistoryMessages": [
    {
      "key": {
        "remoteJid": "94729382772@s.whatsapp.net",
        "fromMe": true,
        "id": "B65C94F8716749046775678E8A87F4E1"
      },
      "messageTimestamp": 1752862837
    },
    {
      "key": {
        "remoteJid": "94729382772@s.whatsapp.net",
        "fromMe": true,
        "id": "D2F4A41EC9CAC81389FDB8962D3B593F"
      },
      "messageTimestamp": 1752862946
    }
  ],
  "nextPreKeyId": 32,
  "firstUnuploadedPreKeyId": 32,
  "accountSyncCounter": 1,
  "accountSettings": {
    "unarchiveChats": false
  },
  "registered": true,
  "pairingCode": "YXZ15BPT",
  "me": {
    "id": "94729382772:20@s.whatsapp.net",
    "lid": "86269233238263:20@lid",
    "name": "ğ˜¿ğ™„ğ™‡ğ™ğ™ƒğ˜¼ğ™‰ ğ™’ğ™€ğ™€ğ™ğ˜¼ğ™ğ™ƒğ™„ğ™‰ğ™‚ğ™ƒğ˜¼"
  },
  "account": {
    "details": "CICl5t4GEM+g6sMGGAEgACgA",
    "accountSignatureKey": "+Ie9LRmmER6G64iJulk+GoDHNd85YwUprTkB74Zc3kM=",
    "accountSignature": "IVesJwUftCyNhH